[
{"name": "A+", "link": "/wiki/A%2B_(programming_language)"},
{"name": "Ada", "link": "/wiki/Ada_(programming_language)"},
{"name": "Analytica", "link": "/wiki/Analytica_(software)"},
{"name": "APL", "link": "/wiki/APL_(programming_language)"},
{"name": "Chapel", "link": "/wiki/Chapel_(programming_language)"},
{"name": "Dartmouth BASIC", "link": "/wiki/Dartmouth_BASIC"},
{"name": "Fortran", "link": "/wiki/Fortran"},
{"name": "Fortran 90", "link": "/wiki/Fortran_90"},
{"name": "FreeMat", "link": "/wiki/FreeMat"},
{"name": "GAUSS", "link": "/wiki/GAUSS_(software)"},
{"name": "Interactive Data Language", "link": "/wiki/Interactive_Data_Language"},
{"name": "J", "link": "/wiki/J_(programming_language)"},
{"name": "Julia", "link": "/wiki/Julia_(programming_language)"},
{"name": "K", "link": "/wiki/K_(programming_language)"},
{"name": "Mathematica", "link": "/wiki/Mathematica"},
{"name": "Wolfram language", "link": "/wiki/Wolfram_language"},
{"name": "MATLAB", "link": "/wiki/MATLAB"},
{"name": "Octave", "link": "/wiki/GNU_Octave"},
{"name": "Q", "link": "/wiki/Q_(programming_language_from_Kx_Systems)"},
{"name": "R", "link": "/wiki/R_(programming_language)"},
{"name": "S", "link": "/wiki/S_(programming_language)"},
{"name": "Scilab", "link": "/wiki/Scilab"},
{"name": "S-Lang", "link": "/wiki/S-Lang"},
{"name": "SequenceL", "link": "/wiki/SequenceL"},
{"name": "Speakeasy", "link": "/wiki/Speakeasy_(computational_environment)"},
{"name": "X10", "link": "/wiki/X10_(programming_language)"},
{"name": "ZPL", "link": "/wiki/ZPL_(programming_language)"},
{"name": "4DOS", "link": "/wiki/4DOS"},
{"name": "IBM PCs", "link": "/wiki/IBM_Personal_Computer"},
{"name": "4OS2", "link": "/wiki/4OS2"},
{"name": "IBM PCs", "link": "/wiki/IBM_Personal_Computer"},
{"name": "bash", "link": "/wiki/Bash_(Unix_shell)"},
{"name": "GNU", "link": "/wiki/GNU"},
{"name": "Free Software Foundation", "link": "/wiki/Free_Software_Foundation"},
{"name": "CLIST", "link": "/wiki/CLIST"},
{"name": "MVS", "link": "/wiki/MVS"},
{"name": "CMS EXEC", "link": "/wiki/CMS_EXEC"},
{"name": "csh", "link": "/wiki/C_shell"},
{"name": "tcsh", "link": "/wiki/Tcsh"},
{"name": "Bill Joy", "link": "/wiki/Bill_Joy"},
{"name": "UC Berkeley", "link": "/wiki/BSD"},
{"name": "DIGITAL Command Language", "link": "/wiki/DIGITAL_Command_Language"},
{"name": "VMS", "link": "/wiki/OpenVMS"},
{"name": "DEC", "link": "/wiki/Digital_Equipment_Corporation"},
{"name": "Compaq", "link": "/wiki/Compaq"},
{"name": "HP", "link": "/wiki/Hewlett-Packard"},
{"name": "DOS batch language", "link": "/wiki/Batch_file"},
{"name": "IBM PC", "link": "/wiki/IBM_Personal_Computer"},
{"name": "DOS", "link": "/wiki/DOS"},
{"name": "Windows", "link": "/wiki/Microsoft_Windows"},
{"name": "EXEC 2", "link": "/wiki/EXEC_2"},
{"name": "Expect", "link": "/wiki/Expect"},
{"name": "Unix", "link": "/wiki/Unix"},
{"name": "fish", "link": "/wiki/Friendly_interactive_shell"},
{"name": "Unix", "link": "/wiki/Unix"},
{"name": "Hamilton C shell", "link": "/wiki/Hamilton_C_shell"},
{"name": "ksh", "link": "/wiki/KornShell"},
{"name": "Unix", "link": "/wiki/Unix"},
{"name": "David Korn", "link": "/wiki/David_Korn_(computer_scientist)"},
{"name": "PowerShell", "link": "/wiki/PowerShell"},
{"name": ".NET", "link": "/wiki/.NET"},
{"name": "Rc", "link": "/wiki/Rc"},
{"name": "Plan 9", "link": "/wiki/Plan_9_from_Bell_Labs"},
{"name": "Rexx", "link": "/wiki/Rexx"},
{"name": "sh", "link": "/wiki/Bourne_shell"},
{"name": "Unix", "link": "/wiki/Unix"},
{"name": "Stephen R. Bourne", "link": "/wiki/Stephen_R._Bourne"},
{"name": "TACL", "link": "/wiki/TACL"},
{"name": "Windows batch language", "link": "/wiki/Batch_file"},
{"name": "COMMAND.COM", "link": "/wiki/COMMAND.COM"},
{"name": "CMD.EXE", "link": "/wiki/CMD.EXE"},
{"name": "zsh", "link": "/wiki/Z_shell"},
{"name": "Unix", "link": "/wiki/Unix"},
{"name": "ActionScript", "link": "/wiki/ActionScript"},
{"name": "Ada", "link": "/wiki/Ada_(programming_language)"},
{"name": "ALGOL 58", "link": "/wiki/ALGOL_58"},
{"name": "ALGOL 60", "link": "/wiki/ALGOL_60"},
{"name": "Ballerina", "link": "/wiki/Ballerina_(programming_language)"},
{"name": "bytecode", "link": "/wiki/Bytecode"},
{"name": "BASIC", "link": "/wiki/BASIC"},
{"name": "BCPL", "link": "/wiki/BCPL"},
{"name": "C", "link": "/wiki/C_(programming_language)"},
{"name": "C++", "link": "/wiki/C%2B%2B"},
{"name": "C#", "link": "/wiki/C_Sharp_(programming_language)"},
{"name": "CIL", "link": "/wiki/Common_Intermediate_Language"},
{"name": "Ceylon", "link": "/wiki/Ceylon_(programming_language)"},
{"name": "JVM", "link": "/wiki/Java_virtual_machine"},
{"name": "bytecode", "link": "/wiki/Bytecode"},
{"name": "CHILL", "link": "/wiki/CHILL"},
{"name": "CLIPPER 5.3", "link": "/wiki/Clipper_(programming_language)"},
{"name": "CLEO", "link": "/wiki/LEO_(computer)"},
{"name": "Clojure", "link": "/wiki/Clojure_(programming_language)"},
{"name": "JVM", "link": "/wiki/Java_virtual_machine"},
{"name": "bytecode", "link": "/wiki/Bytecode"},
{"name": "COBOL", "link": "/wiki/COBOL"},
{"name": "Cobra", "link": "/wiki/Cobra_(programming_language)"},
{"name": "Common Lisp", "link": "/wiki/Common_Lisp"},
{"name": "Crystal", "link": "/wiki/Crystal_(programming_language)"},
{"name": "Curl", "link": "/wiki/Curl_(programming_language)"},
{"name": "D", "link": "/wiki/D_(programming_language)"},
{"name": "DASL", "link": "/wiki/Distributed_Application_Specification_Language"},
{"name": "JS", "link": "/wiki/JavaScript"},
{"name": "Delphi", "link": "/wiki/Delphi_(programming_language)"},
{"name": "Borland", "link": "/wiki/Borland"},
{"name": "Object Pascal", "link": "/wiki/Object_Pascal"},
{"name": "DIBOL", "link": "/wiki/DIBOL"},
{"name": "Dylan", "link": "/wiki/Dylan_(programming_language)"},
{"name": "eC", "link": "/wiki/EC_(programming_language)"},
{"name": "Eiffel", "link": "/wiki/Eiffel_(programming_language)"},
{"name": "Bertrand Meyer", "link": "/wiki/Bertrand_Meyer"},
{"name": "Elm", "link": "/wiki/Elm_(programming_language)"},
{"name": "Emacs Lisp", "link": "/wiki/Emacs_Lisp"},
{"name": "Emerald", "link": "/wiki/Emerald_(programming_language)"},
{"name": "Erlang", "link": "/wiki/Erlang_(programming_language)"},
{"name": "F#", "link": "/wiki/F_Sharp_(programming_language)"},
{"name": "CIL", "link": "/wiki/Common_Intermediate_Language"},
{"name": "Factor", "link": "/wiki/Factor_(programming_language)"},
{"name": "Fortran", "link": "/wiki/Fortran"},
{"name": "IBM", "link": "/wiki/IBM"},
{"name": "John Backus", "link": "/wiki/John_Backus"},
{"name": "GAUSS", "link": "/wiki/GAUSS_(software)"},
{"name": "Genie", "link": "/wiki/Genie_(programming_language)"},
{"name": "Go", "link": "/wiki/Go_(programming_language)"},
{"name": "Gosu", "link": "/wiki/Gosu_(programming_language)"},
{"name": "JVM", "link": "/wiki/Java_virtual_machine"},
{"name": "bytecode", "link": "/wiki/Bytecode"},
{"name": "Groovy", "link": "/wiki/Groovy_(programming_language)"},
{"name": "JVM", "link": "/wiki/Java_virtual_machine"},
{"name": "bytecode", "link": "/wiki/Bytecode"},
{"name": "Haskell", "link": "/wiki/Haskell"},
{"name": "Harbour", "link": "/wiki/Harbour_(software)"},
{"name": "HolyC", "link": "/wiki/TempleOS"},
{"name": "Inform", "link": "/wiki/Inform"},
{"name": "Glulx", "link": "/wiki/Glulx"},
{"name": "Z-code", "link": "/wiki/Z-machine"},
{"name": "Java", "link": "/wiki/Java_(programming_language)"},
{"name": "JVM", "link": "/wiki/Java_virtual_machine"},
{"name": "bytecode", "link": "/wiki/Bytecode"},
{"name": "machine code", "link": "/wiki/Machine_code"},
{"name": "JOVIAL", "link": "/wiki/JOVIAL"},
{"name": "Julia", "link": "/wiki/Julia_(programming_language)"},
{"name": "Kotlin", "link": "/wiki/Kotlin_(programming_language)"},
{"name": "LLVM", "link": "/wiki/LLVM"},
{"name": "LabVIEW", "link": "/wiki/LabVIEW"},
{"name": "Mercury", "link": "/wiki/Mercury_(programming_language)"},
{"name": "Mesa", "link": "/wiki/Mesa_(programming_language)"},
{"name": "Nemerle", "link": "/wiki/Nemerle"},
{"name": "Nim", "link": "/wiki/Nim_(programming_language)"},
{"name": "Objective-C", "link": "/wiki/Objective-C"},
{"name": "P", "link": "/wiki/P_(programming_language)"},
{"name": "Pascal", "link": "/wiki/Pascal_(programming_language)"},
{"name": "PL/I", "link": "/wiki/PL/I"},
{"name": "Plus", "link": "/wiki/Plus_(programming_language)"},
{"name": "Python", "link": "/wiki/Python_(programming_language)"},
{"name": "VM", "link": "/wiki/Virtual_machine"},
{"name": "bytecode", "link": "/wiki/Bytecode"},
{"name": "RPG", "link": "/wiki/IBM_RPG"},
{"name": "Rust", "link": "/wiki/Rust_(programming_language)"},
{"name": "Scala", "link": "/wiki/Scala_(programming_language)"},
{"name": "JVM", "link": "/wiki/Java_virtual_machine"},
{"name": "bytecode", "link": "/wiki/Bytecode"},
{"name": "Scheme", "link": "/wiki/Scheme_(programming_language)"},
{"name": "SequenceL", "link": "/wiki/SequenceL"},
{"name": "Simula", "link": "/wiki/Simula"},
{"name": "ALGOL 60", "link": "/wiki/ALGOL_60"},
{"name": "Smalltalk", "link": "/wiki/Smalltalk"},
{"name": "VM", "link": "/wiki/Virtual_machine"},
{"name": "bytecode", "link": "/wiki/Bytecode"},
{"name": "Swift", "link": "/wiki/Swift_(programming_language)"},
{"name": "ML", "link": "/wiki/ML_(programming_language)"},
{"name": "Turing", "link": "/wiki/Turing_(programming_language)"},
{"name": "Vala", "link": "/wiki/Vala_(programming_language)"},
{"name": "Visual Basic", "link": "/wiki/Visual_Basic"},
{"name": "CIL", "link": "/wiki/Common_Intermediate_Language"},
{"name": "Visual FoxPro", "link": "/wiki/Visual_FoxPro"},
{"name": "Visual Prolog", "link": "/wiki/Visual_Prolog"},
{"name": "Xojo", "link": "/wiki/Xojo"},
{"name": "Ada", "link": "/wiki/Ada_(programming_language)"},
{"name": "Alef", "link": "/wiki/Alef_(programming_language)"},
{"name": "Plan 9 from Bell Labs", "link": "/wiki/Plan_9_from_Bell_Labs"},
{"name": "Ateji PX", "link": "/wiki/Ateji_PX"},
{"name": "Ballerina", "link": "/wiki/Ballerina_(programming_language)"},
{"name": "ChucK", "link": "/wiki/ChucK"},
{"name": "Cilk", "link": "/wiki/Cilk"},
{"name": "C", "link": "/wiki/C_(programming_language)"},
{"name": "Cω", "link": "/wiki/C%CF%89"},
{"name": "Clojure", "link": "/wiki/Clojure"},
{"name": "Lisp", "link": "/wiki/Lisp_(programming_language)"},
{"name": "Java virtual machine", "link": "/wiki/Java_virtual_machine"},
{"name": "Chapel", "link": "/wiki/Chapel_(programming_language)"},
{"name": "Co-array Fortran", "link": "/wiki/Co-array_Fortran"},
{"name": "Concurrent Pascal", "link": "/wiki/Concurrent_Pascal"},
{"name": "Curry", "link": "/wiki/Curry_(programming_language)"},
{"name": "E", "link": "/wiki/E_(programming_language)"},
{"name": "Eiffel", "link": "/wiki/Eiffel_(programming_language)"},
{"name": "SCOOP", "link": "/wiki/SCOOP_(software)"},
{"name": "Elixir", "link": "/wiki/Elixir_(programming_language)"},
{"name": "Emerald", "link": "/wiki/Emerald_(programming_language)"},
{"name": "Erlang", "link": "/wiki/Erlang_(programming_language)"},
{"name": "Gambit Scheme", "link": "/wiki/Gambit_(scheme_implementation)"},
{"name": "Go", "link": "/wiki/Go_(programming_language)"},
{"name": "Haskell", "link": "/wiki/Haskell"},
{"name": "Java", "link": "/wiki/Java_(programming_language)"},
{"name": "Julia", "link": "/wiki/Julia_(programming_language)"},
{"name": "Joule", "link": "/wiki/Joule_(programming_language)"},
{"name": "LabVIEW", "link": "/wiki/LabVIEW"},
{"name": "Limbo", "link": "/wiki/Limbo_(programming_language)"},
{"name": "Alef", "link": "/wiki/Alef_(programming_language)"},
{"name": "Inferno (operating system)", "link": "/wiki/Inferno_(operating_system)"},
{"name": "MultiLisp", "link": "/wiki/MultiLisp"},
{"name": "Scheme", "link": "/wiki/Scheme_(programming_language)"},
{"name": "OCaml", "link": "/wiki/OCaml"},
{"name": "occam", "link": "/wiki/Occam_(programming_language)"},
{"name": "Communicating Sequential Processes", "link": "/wiki/Communicating_sequential_processes"},
{"name": "Orc", "link": "/wiki/Orc_(programming_language)"},
{"name": "Oz", "link": "/wiki/Oz_(programming_language)"},
{"name": "cross-platform", "link": "/wiki/Cross-platform"},
{"name": "P", "link": "/wiki/P_(programming_language)"},
{"name": "Pict", "link": "/wiki/Pict_(programming_language)"},
{"name": "π-calculus", "link": "/wiki/%CE%A0-calculus"},
{"name": "Python", "link": "/wiki/Python_(programming_language)"},
{"name": "Rust", "link": "/wiki/Rust_(programming_language)"},
{"name": "Scala", "link": "/wiki/Scala_(programming_language)"},
{"name": "actors", "link": "/wiki/Actor_model"},
{"name": "SequenceL", "link": "/wiki/SequenceL"},
{"name": "SR", "link": "/wiki/SR_(programming_language)"},
{"name": "Unified Parallel C", "link": "/wiki/Unified_Parallel_C"},
{"name": "XProc", "link": "/wiki/XProc"},
{"name": "ABCL/c+", "link": "/wiki/Actor-Based_Concurrent_Language"},
{"name": "Alef", "link": "/wiki/Alef_(programming_language)"},
{"name": "AWK", "link": "/wiki/AWK"},
{"name": "B", "link": "/wiki/B_(programming_language)"},
{"name": "bc", "link": "/wiki/Bc_(programming_language)"},
{"name": "BCPL", "link": "/wiki/BCPL"},
{"name": "Ballerina", "link": "/wiki/Ballerina_(programming_language)"},
{"name": "C", "link": "/wiki/C_(programming_language)"},
{"name": "Bell Labs", "link": "/wiki/Bell_Labs"},
{"name": "C++", "link": "/wiki/C%2B%2B"},
{"name": "C#", "link": "/wiki/C_Sharp_(programming_language)"},
{"name": "Ceylon", "link": "/wiki/Ceylon_(programming_language)"},
{"name": "ChucK", "link": "/wiki/ChucK"},
{"name": "Cilk", "link": "/wiki/Cilk"},
{"name": "Cyclone", "link": "/wiki/Cyclone_(programming_language)"},
{"name": "D", "link": "/wiki/D_(programming_language)"},
{"name": "Dart", "link": "/wiki/Dart_(programming_language)"},
{"name": "DASL", "link": "/wiki/Distributed_Application_Specification_Language"},
{"name": "E", "link": "/wiki/E_(programming_language)"},
{"name": "eC", "link": "/wiki/EC_(programming_language)"},
{"name": "ECMAScript", "link": "/wiki/ECMAScript"},
{"name": "GLSL", "link": "/wiki/OpenGL_Shading_Language"},
{"name": "Go", "link": "/wiki/Go_(programming_language)"},
{"name": "HLSL", "link": "/wiki/High-Level_Shading_Language"},
{"name": "Java", "link": "/wiki/Java_(programming_language)"},
{"name": "Limbo", "link": "/wiki/Limbo_(programming_language)"},
{"name": "LPC", "link": "/wiki/LPC_(programming_language)"},
{"name": "MEL", "link": "/wiki/Maya_Embedded_Language"},
{"name": "Nemerle", "link": "/wiki/Nemerle"},
{"name": "Objective-C", "link": "/wiki/Objective-C"},
{"name": "PCASTL", "link": "/wiki/PCASTL"},
{"name": "Perl", "link": "/wiki/Perl"},
{"name": "PHP", "link": "/wiki/PHP"},
{"name": "Pico", "link": "/wiki/Pico_(programming_language)"},
{"name": "Pike", "link": "/wiki/Pike_(programming_language)"},
{"name": "PowerShell", "link": "/wiki/PowerShell"},
{"name": "R", "link": "/wiki/R_(programming_language)"},
{"name": "Rust", "link": "/wiki/Rust_(programming_language)"},
{"name": "S-Lang", "link": "/wiki/S-Lang"},
{"name": "Scala", "link": "/wiki/Scala_(programming_language)"},
{"name": "sed", "link": "/wiki/Sed"},
{"name": "Solidity", "link": "/wiki/Solidity_(programming_language)"},
{"name": "SuperCollider", "link": "/wiki/SuperCollider"},
{"name": "Swift", "link": "/wiki/Swift_(programming_language)"},
{"name": "UnrealScript", "link": "/wiki/UnrealScript"},
{"name": "Yorick", "link": "/wiki/Yorick_(programming_language)"},
{"name": "YASS", "link": "/wiki/Zenith_Parsing_Engine"},
{"name": "Analytica", "link": "/wiki/Analytica_(software)"},
{"name": "Ballerina", "link": "/wiki/Ballerina_(programming_language)"},
{"name": "BMDFM", "link": "/wiki/BMDFM"},
{"name": "Hartmann pipelines", "link": "/wiki/Hartmann_pipeline"},
{"name": "LabVIEW", "link": "/wiki/LabVIEW"},
{"name": "Lucid", "link": "/wiki/Lucid_(programming_language)"},
{"name": "Max", "link": "/wiki/Max_(software)"},
{"name": "Oz", "link": "/wiki/Oz_(programming_language)"},
{"name": "Prograph", "link": "/wiki/Prograph"},
{"name": "Pure Data", "link": "/wiki/Pure_Data"},
{"name": "Reaktor", "link": "/wiki/Reaktor"},
{"name": "StreamBase StreamSQL EventFlow", "link": "/wiki/StreamBase_Systems#StreamSQL_EventFlow_Language"},
{"name": "Swift (parallel scripting language)", "link": "/wiki/Swift_(parallel_scripting_language)"},
{"name": "VEE", "link": "/wiki/Agilent_VEE"},
{"name": "VHDL", "link": "/wiki/VHDL"},
{"name": "VisSim", "link": "/wiki/VisSim"},
{"name": "Vvvv", "link": "/wiki/Vvvv"},
{"name": "WebMethods Flow", "link": "/wiki/WebMethods_Flow"},
{"name": "Clarion", "link": "/wiki/Clarion_(programming_language)"},
{"name": "Clipper", "link": "/wiki/Clipper_(programming_language)"},
{"name": "dBase", "link": "/wiki/DBase"},
{"name": "Gremlin", "link": "/wiki/Gremlin_(programming_language)"},
{"name": "Mathematica", "link": "/wiki/Mathematica"},
{"name": "Wolfram language", "link": "/wiki/Wolfram_language"},
{"name": "MUMPS", "link": "/wiki/MUMPS"},
{"name": "Caché ObjectScript", "link": "/wiki/Cach%C3%A9_ObjectScript"},
{"name": "RDQL", "link": "/wiki/RDQL"},
{"name": "SPARQL", "link": "/wiki/SPARQL"},
{"name": "SQL", "link": "/wiki/SQL"},
{"name": "Visual FoxPro", "link": "/wiki/Visual_FoxPro"},
{"name": "WebDNA", "link": "/wiki/WebDNA"},
{"name": "Analytica", "link": "/wiki/Analytica_(software)"},
{"name": "Ant", "link": "/wiki/Apache_Ant"},
{"name": "declarative programming", "link": "/wiki/Declarative_programming"},
{"name": "imperative programming", "link": "/wiki/Imperative_programming"},
{"name": "Curry", "link": "/wiki/Curry_(programming_language)"},
{"name": "Cypher", "link": "/wiki/Cypher_(query_language)"},
{"name": "Datalog", "link": "/wiki/Datalog"},
{"name": "Distributed Application Specification Language", "link": "/wiki/Distributed_Application_Specification_Language"},
{"name": "declarative programming", "link": "/wiki/Declarative_programming"},
{"name": "imperative programming", "link": "/wiki/Imperative_programming"},
{"name": "ECL", "link": "/wiki/ECL_(data-centric_programming_language)"},
{"name": "Gremlin", "link": "/wiki/Gremlin_(programming_language)"},
{"name": "Inform", "link": "/wiki/Inform"},
{"name": "declarative programming", "link": "/wiki/Declarative_programming"},
{"name": "imperative programming", "link": "/wiki/Imperative_programming"},
{"name": "Lustre", "link": "/wiki/Lustre_(programming_language)"},
{"name": "Mathematica", "link": "/wiki/Mathematica"},
{"name": "Wolfram language", "link": "/wiki/Wolfram_language"},
{"name": "Mercury", "link": "/wiki/Mercury_(programming_language)"},
{"name": "MetaPost", "link": "/wiki/MetaPost"},
{"name": "Modelica", "link": "/wiki/Modelica"},
{"name": "Prolog", "link": "/wiki/Prolog"},
{"name": "QML", "link": "/wiki/QML"},
{"name": "Oz", "link": "/wiki/Oz_(programming_language)"},
{"name": "RDQL", "link": "/wiki/RDQL"},
{"name": "SequenceL", "link": "/wiki/SequenceL"},
{"name": "SPARQL", "link": "/wiki/SPARQL"},
{"name": "SQL", "link": "/wiki/SQL"},
{"name": "Soufflé", "link": "/wiki/Souffl%C3%A9_(programming_language)"},
{"name": "xBase", "link": "/wiki/XBase"},
{"name": "XSL Transformations", "link": "/wiki/XSL_Transformations"},
{"name": "AngelScript", "link": "/wiki/AngelScript"},
{"name": "Ch", "link": "/wiki/Ch_(computer_programming)"},
{"name": "EEL", "link": "/wiki/Extensible_Embeddable_Language"},
{"name": "Io", "link": "/wiki/Io_(programming_language)"},
{"name": "jq", "link": "/wiki/Jq_(programming_language)"},
{"name": "Julia", "link": "/wiki/Julia_(programming_language)"},
{"name": "Lua", "link": "/wiki/Lua_(programming_language)"},
{"name": "Python", "link": "/wiki/Python_(programming_language)"},
{"name": "Ring", "link": "/wiki/Ring_(programming_language)"},
{"name": "Ruby", "link": "/wiki/Ruby_(programming_language)"},
{"name": "mruby", "link": "/wiki/Mruby"},
{"name": "Squirrel", "link": "/wiki/Squirrel_(programming_language)"},
{"name": "Tcl", "link": "/wiki/Tcl"},
{"name": "Alice", "link": "/wiki/Alice_(software)"},
{"name": "Blockly", "link": "/wiki/Blockly"},
{"name": "Catrobat", "link": "/wiki/Catrobat"},
{"name": "COMAL", "link": "/wiki/COMAL_(programming_language)"},
{"name": "Elan", "link": "/wiki/ELAN_(programming_language)"},
{"name": "Emerald", "link": "/wiki/Emerald_(programming_language)"},
{"name": "Ezhil", "link": "/wiki/Ezhil_(programming_language)"},
{"name": "Logo", "link": "/wiki/Logo_(programming_language)"},
{"name": "Mathematica", "link": "/wiki/Mathematica"},
{"name": "Wolfram language", "link": "/wiki/Wolfram_language"},
{"name": "Modula-2", "link": "/wiki/Modula-2"},
{"name": "Pascal", "link": "/wiki/Pascal_(programming_language)"},
{"name": "Racket", "link": "/wiki/Racket_(programming_language)"},
{"name": "Scheme", "link": "/wiki/Scheme_(programming_language)"},
{"name": "Scratch", "link": "/wiki/Scratch_(programming_language)"},
{"name": "Snap!", "link": "/wiki/Snap!_(programming_language)"},
{"name": "Turing", "link": "/wiki/Turing_(programming_language)"},
{"name": "Beatnik", "link": "/wiki/Beatnik_(programming_language)"},
{"name": "Befunge", "link": "/wiki/Befunge"},
{"name": "Brainfuck", "link": "/wiki/Brainfuck"},
{"name": "Chef", "link": "/wiki/Chef_(programming_language)"},
{"name": "INTERCAL", "link": "/wiki/INTERCAL"},
{"name": "LOLCODE", "link": "/wiki/LOLCODE"},
{"name": "Malbolge", "link": "/wiki/Malbolge"},
{"name": "Piet", "link": "/wiki/Piet_(programming_language)"},
{"name": "Shakespeare", "link": "/wiki/Shakespeare_(programming_language)"},
{"name": "Thue", "link": "/wiki/Thue_(programming_language)"},
{"name": "Whitespace", "link": "/wiki/Whitespace_(programming_language)"},
{"name": "AutoLISP", "link": "/wiki/AutoLISP"},
{"name": "AutoCAD", "link": "/wiki/AutoCAD"},
{"name": "BeanShell", "link": "/wiki/BeanShell"},
{"name": "CAL", "link": "/wiki/Cakewalk_(sequencer)#Features"},
{"name": "C/AL", "link": "/wiki/C/AL"},
{"name": "Guile", "link": "/wiki/GNU_Guile"},
{"name": "Emacs Lisp", "link": "/wiki/Emacs_Lisp"},
{"name": "JavaScript", "link": "/wiki/JavaScript"},
{"name": "JScript", "link": "/wiki/JScript"},
{"name": "Lua", "link": "/wiki/Lua_(programming_language)"},
{"name": "OpenCL", "link": "/wiki/OpenCL"},
{"name": "OptimJ", "link": "/wiki/OptimJ"},
{"name": "Perl", "link": "/wiki/Perl"},
{"name": "Pike", "link": "/wiki/Pike_(programming_language)"},
{"name": "PowerShell", "link": "/wiki/PowerShell"},
{"name": "Python", "link": "/wiki/Python_(programming_language)"},
{"name": "Rexx", "link": "/wiki/Rexx"},
{"name": "Ring", "link": "/wiki/Ring_(programming_language)"},
{"name": "Ruby", "link": "/wiki/Ruby_(programming_language)"},
{"name": "S-Lang", "link": "/wiki/S-Lang"},
{"name": "SQL", "link": "/wiki/SQL"},
{"name": "Squirrel", "link": "/wiki/Squirrel_(programming_language)"},
{"name": "Tcl", "link": "/wiki/Tcl"},
{"name": "Vim script", "link": "/wiki/Vim_script"},
{"name": "Visual Basic for Applications", "link": "/wiki/Visual_Basic_for_Applications"},
{"name": "1C:Enterprise programming language", "link": "/wiki/1C:Enterprise_programming_language"},
{"name": "ABAP", "link": "/wiki/ABAP"},
{"name": "CorVision", "link": "/wiki/CorVision"},
{"name": "CSC", "link": "/wiki/Computer_Sciences_Corporation"},
{"name": "CA-IDEAL", "link": "/wiki/DATACOM/DB"},
{"name": "CA-DATACOM/DB", "link": "/wiki/DATACOM/DB"},
{"name": "Easytrieve", "link": "/wiki/Easytrieve"},
{"name": "FOCUS", "link": "/wiki/FOCUS"},
{"name": "IBM Informix-4GL", "link": "/wiki/IBM_Informix-4GL"},
{"name": "LINC 4GL", "link": "/wiki/LINC_4GL"},
{"name": "MAPPER", "link": "/wiki/MAPPER"},
{"name": "Unisys/Sperry", "link": "/wiki/Unisys"},
{"name": "MARK-IV", "link": "/wiki/MARK_IV_(software)"},
{"name": "Sterling/Informatics", "link": "/wiki/Sterling_Software"},
{"name": "NATURAL", "link": "/wiki/NATURAL"},
{"name": "Progress 4GL", "link": "/wiki/Progress_4GL"},
{"name": "PV-Wave", "link": "/wiki/PV-Wave"},
{"name": "LiveCode", "link": "/wiki/LiveCode"},
{"name": "SAS", "link": "/wiki/SAS_System"},
{"name": "SQL", "link": "/wiki/SQL"},
{"name": "Ubercode", "link": "/wiki/Ubercode"},
{"name": "Uniface", "link": "/wiki/Uniface_(programming_language)"},
{"name": "Visual DataFlex", "link": "/wiki/Visual_DataFlex"},
{"name": "Visual FoxPro", "link": "/wiki/Visual_FoxPro"},
{"name": "xBase", "link": "/wiki/XBase"},
{"name": "Agda", "link": "/wiki/Agda_(programming_language)"},
{"name": "Clean", "link": "/wiki/Clean_(programming_language)"},
{"name": "Coq", "link": "/wiki/Coq"},
{"name": "Cuneiform", "link": "/wiki/Cuneiform_(programming_language)"},
{"name": "Curry", "link": "/wiki/Curry_(programming_language)"},
{"name": "Elm", "link": "/wiki/Elm_(programming_language)"},
{"name": "Futhark", "link": "/wiki/Futhark_(programming_language)"},
{"name": "Haskell", "link": "/wiki/Haskell"},
{"name": "Hope", "link": "/wiki/Hope_(programming_language)"},
{"name": "Idris", "link": "/wiki/Idris_(programming_language)"},
{"name": "Joy", "link": "/wiki/Joy_(programming_language)"},
{"name": "jq", "link": "/wiki/Jq_(programming_language)"},
{"name": "Lean", "link": "/wiki/Lean_(proof_assistant)"},
{"name": "Mercury", "link": "/wiki/Mercury_(programming_language)"},
{"name": "Miranda", "link": "/wiki/Miranda_(programming_language)"},
{"name": "PureScript", "link": "/wiki/PureScript"},
{"name": "Ur", "link": "/wiki/Ur_(programming_language)"},
{"name": "KRC", "link": "/wiki/Kent_Recursive_Calculator"},
{"name": "SAC", "link": "/wiki/SAC_programming_language"},
{"name": "SASL", "link": "/wiki/SASL_(programming_language)"},
{"name": "SequenceL", "link": "/wiki/SequenceL"},
{"name": "APL", "link": "/wiki/APL_(programming_language)"},
{"name": "ATS", "link": "/wiki/ATS_(programming_language)"},
{"name": "CAL", "link": "/wiki/CAL_(programming_language)"},
{"name": "C++", "link": "/wiki/C%2B%2B"},
{"name": "C++11", "link": "/wiki/C%2B%2B11"},
{"name": "C#", "link": "/wiki/C_Sharp_(programming_language)"},
{"name": "VB.NET", "link": "/wiki/VB.NET"},
{"name": "Ceylon", "link": "/wiki/Ceylon_(programming_language)"},
{"name": "Curl", "link": "/wiki/Curl_(programming_language)"},
{"name": "D", "link": "/wiki/D_(programming_language)"},
{"name": "Dart", "link": "/wiki/Dart_(programming_language)"},
{"name": "ECMAScript", "link": "/wiki/ECMAScript"},
{"name": "Erlang", "link": "/wiki/Erlang_(programming_language)"},
{"name": "F#", "link": "/wiki/F_Sharp_(programming_language)"},
{"name": "Fexl", "link": "/w/index.php?title=Fexl_(programming_language)&action=edit&redlink=1"},
{"name": "Flix", "link": "/wiki/Flix_(programming_language)"},
{"name": "G (used in LabVIEW)", "link": "/wiki/LabVIEW"},
{"name": "Groovy", "link": "/wiki/Groovy_(programming_language)"},
{"name": "Hop", "link": "/wiki/Hop_(software)"},
{"name": "J", "link": "/wiki/J_(programming_language)"},
{"name": "Java (since version 8)", "link": "/wiki/Java_(programming_language)"},
{"name": "Julia", "link": "/wiki/Julia_(programming_language)"},
{"name": "Kotlin", "link": "/wiki/Kotlin_(programming_language)"},
{"name": "Lisp", "link": "/wiki/Lisp_(programming_language)"},
{"name": "Mathematica", "link": "/wiki/Mathematica"},
{"name": "Wolfram language", "link": "/wiki/Wolfram_language"},
{"name": "ML", "link": "/wiki/ML_(programming_language)"},
{"name": "Nemerle", "link": "/wiki/Nemerle"},
{"name": "Nim", "link": "/wiki/Nim_(programming_language)"},
{"name": "Opal", "link": "/wiki/Opal_(programming_language)"},
{"name": "OPS5", "link": "/wiki/OPS5"},
{"name": "Perl", "link": "/wiki/Perl"},
{"name": "PHP", "link": "/wiki/PHP"},
{"name": "Python", "link": "/wiki/Python_(programming_language)"},
{"name": "Q (equational programming language)", "link": "/wiki/Q_(equational_programming_language)"},
{"name": "Q (programming language from Kx Systems)", "link": "/wiki/Q_(programming_language_from_Kx_Systems)"},
{"name": "R", "link": "/wiki/R_(programming_language)"},
{"name": "Raku", "link": "/wiki/Raku_(programming_language)"},
{"name": "REBOL", "link": "/wiki/REBOL"},
{"name": "Red", "link": "/wiki/Red_(programming_language)"},
{"name": "Ring", "link": "/wiki/Ring_(programming_language)"},
{"name": "Ruby", "link": "/wiki/Ruby_(programming_language)"},
{"name": "REFAL", "link": "/wiki/REFAL"},
{"name": "Rust", "link": "/wiki/Rust_(programming_language)"},
{"name": "Scala", "link": "/wiki/Scala_(programming_language)"},
{"name": "Swift", "link": "/wiki/Swift_(programming_language)"},
{"name": "Spreadsheets", "link": "/wiki/Spreadsheet"},
{"name": "Tcl", "link": "/wiki/Tcl"},
{"name": "Advanced Boolean Expression Language", "link": "/wiki/Advanced_Boolean_Expression_Language"},
{"name": "Altera Hardware Description Language", "link": "/wiki/Altera_Hardware_Description_Language"},
{"name": "Bluespec", "link": "/wiki/Bluespec"},
{"name": "Confluence", "link": "/wiki/Confluence"},
{"name": "ELLA", "link": "/wiki/ELLA_(programming_language)"},
{"name": "Handel-C", "link": "/wiki/Handel-C"},
{"name": "Impulse C", "link": "/wiki/Impulse_C"},
{"name": "Lava", "link": "/wiki/Lava_(programming_language)"},
{"name": "Lola", "link": "/wiki/Lola_(computing)"},
{"name": "MyHDL", "link": "/wiki/MyHDL"},
{"name": "PALASM", "link": "/wiki/PALASM"},
{"name": "Ruby (hardware description language)", "link": "/wiki/Ruby_(hardware_description_language)"},
{"name": "SystemC", "link": "/wiki/SystemC"},
{"name": "SystemVerilog", "link": "/wiki/SystemVerilog"},
{"name": "Verilog", "link": "/wiki/Verilog"},
{"name": "VHDL", "link": "/wiki/VHDL"},
{"name": "Ada", "link": "/wiki/Ada_(programming_language)"},
{"name": "ALGOL 58", "link": "/wiki/ALGOL_58"},
{"name": "ALGOL 60", "link": "/wiki/ALGOL_60"},
{"name": "BASIC", "link": "/wiki/BASIC"},
{"name": "C", "link": "/wiki/C_(programming_language)"},
{"name": "C++", "link": "/wiki/C%2B%2B"},
{"name": "C#", "link": "/wiki/C_Sharp_(programming_language)"},
{"name": "Ceylon", "link": "/wiki/Ceylon_(programming_language)"},
{"name": "CHILL", "link": "/wiki/CHILL"},
{"name": "COBOL", "link": "/wiki/COBOL"},
{"name": "D", "link": "/wiki/D_(programming_language)"},
{"name": "Dart", "link": "/wiki/Dart_(programming_language)"},
{"name": "ECMAScript", "link": "/wiki/ECMAScript"},
{"name": "FORTRAN", "link": "/wiki/FORTRAN"},
{"name": "GAUSS", "link": "/wiki/GAUSS_(software)"},
{"name": "Go", "link": "/wiki/Go_(programming_language)"},
{"name": "Groovy", "link": "/wiki/Groovy_(programming_language)"},
{"name": "Icon", "link": "/wiki/Icon_(programming_language)"},
{"name": "Java", "link": "/wiki/Java_(programming_language)"},
{"name": "Julia", "link": "/wiki/Julia_(programming_language)"},
{"name": "Lua", "link": "/wiki/Lua_(programming_language)"},
{"name": "Mathematica", "link": "/wiki/Mathematica"},
{"name": "Wolfram language", "link": "/wiki/Wolfram_language"},
{"name": "MATLAB", "link": "/wiki/MATLAB"},
{"name": "Machine languages", "link": "/wiki/Machine_code"},
{"name": "Modula-2", "link": "/wiki/Modula-2"},
{"name": "Modula-3", "link": "/wiki/Modula-3"},
{"name": "MUMPS", "link": "/wiki/MUMPS"},
{"name": "Nim", "link": "/wiki/Nim_(programming_language)"},
{"name": "OCaml", "link": "/wiki/OCaml"},
{"name": "Oberon", "link": "/wiki/Oberon_(programming_language)"},
{"name": "Object Pascal", "link": "/wiki/Object_Pascal"},
{"name": "Open Object Rexx", "link": "/wiki/Object_REXX"},
{"name": "Open Programming Language", "link": "/wiki/Open_Programming_Language"},
{"name": "OpenEdge Advanced Business Language", "link": "/wiki/OpenEdge_Advanced_Business_Language"},
{"name": "Pascal", "link": "/wiki/Pascal_(programming_language)"},
{"name": "Perl", "link": "/wiki/Perl"},
{"name": "PHP", "link": "/wiki/PHP"},
{"name": "PL/I", "link": "/wiki/PL/I"},
{"name": "PL/S", "link": "/wiki/IBM_PL/S"},
{"name": "PowerShell", "link": "/wiki/PowerShell"},
{"name": "PROSE", "link": "/wiki/PROSE_modeling_language"},
{"name": "Python", "link": "/wiki/Python_(programming_language)"},
{"name": "Rexx", "link": "/wiki/Rexx"},
{"name": "Ring", "link": "/wiki/Ring_(programming_language)"},
{"name": "Ruby", "link": "/wiki/Ruby_(programming_language)"},
{"name": "Rust", "link": "/wiki/Rust_(programming_language)"},
{"name": "SETL", "link": "/wiki/SETL"},
{"name": "Speakeasy", "link": "/wiki/Speakeasy_(computational_environment)"},
{"name": "Swift", "link": "/wiki/Swift_(programming_language)"},
{"name": "Tcl", "link": "/wiki/Tcl"},
{"name": "APL", "link": "/wiki/APL_(programming_language)"},
{"name": "BASIC", "link": "/wiki/BASIC"},
{"name": "Clojure", "link": "/wiki/Clojure"},
{"name": "Common Lisp", "link": "/wiki/Common_Lisp"},
{"name": "Dart", "link": "/wiki/Dart_(programming_language)"},
{"name": "ECMAScript", "link": "/wiki/ECMAScript"},
{"name": "Erlang", "link": "/wiki/Erlang_(programming_language)"},
{"name": "Elixir", "link": "/wiki/Elixir_(programming_language)"},
{"name": "F#", "link": "/wiki/F_Sharp_(programming_language)"},
{"name": "Fril", "link": "/wiki/Fril"},
{"name": "GAUSS", "link": "/wiki/GAUSS_(software)"},
{"name": "Groovy", "link": "/wiki/Groovy_(programming_language)"},
{"name": "Guile", "link": "/wiki/GNU_Guile"},
{"name": "Haskell", "link": "/wiki/Haskell"},
{"name": "IDL", "link": "/wiki/IDL_(programming_language)"},
{"name": "J", "link": "/wiki/J_(programming_language)"},
{"name": "Java", "link": "/wiki/Java_(programming_language)"},
{"name": "Julia", "link": "/wiki/Julia_(programming_language)"},
{"name": "Lua", "link": "/wiki/Lua_(programming_language)"},
{"name": "MUMPS", "link": "/wiki/MUMPS"},
{"name": "Maple", "link": "/wiki/Maple_(software)"},
{"name": "Mathematica", "link": "/wiki/Mathematica"},
{"name": "Wolfram language", "link": "/wiki/Wolfram_language"},
{"name": "MATLAB", "link": "/wiki/MATLAB"},
{"name": "ML", "link": "/wiki/ML_(programming_language)"},
{"name": "OCaml", "link": "/wiki/OCaml"},
{"name": "Perl", "link": "/wiki/Perl"},
{"name": "PHP", "link": "/wiki/PHP"},
{"name": "Pike", "link": "/wiki/Pike_(programming_language)"},
{"name": "PostScript", "link": "/wiki/PostScript"},
{"name": "PowerShell", "link": "/wiki/PowerShell"},
{"name": ".NET", "link": "/wiki/.NET"},
{"name": "Prolog", "link": "/wiki/Prolog_(programming_language)"},
{"name": "Python", "link": "/wiki/Python_(programming_language)"},
{"name": "PROSE", "link": "/wiki/PROSE_modeling_language"},
{"name": "R", "link": "/wiki/R_(programming_language)"},
{"name": "REBOL", "link": "/wiki/REBOL"},
{"name": "Rexx", "link": "/wiki/Rexx"},
{"name": "Ring", "link": "/wiki/Ring_(programming_language)"},
{"name": "Ruby", "link": "/wiki/Ruby_(programming_language)"},
{"name": "IRB", "link": "/wiki/Interactive_Ruby_Shell"},
{"name": "Scala", "link": "/wiki/Scala_(programming_language)"},
{"name": "Scheme", "link": "/wiki/Scheme_(programming_language)"},
{"name": "Smalltalk", "link": "/wiki/Smalltalk"},
{"name": "S-Lang", "link": "/wiki/S-Lang"},
{"name": "Speakeasy", "link": "/wiki/Speakeasy_(computational_environment)"},
{"name": "Swift", "link": "/wiki/Swift_(programming_language)"},
{"name": "Tcl", "link": "/wiki/Tcl"},
{"name": "Unix shell", "link": "/wiki/Unix_shell"},
{"name": "Visual FoxPro", "link": "/wiki/Visual_FoxPro"},
{"name": "Ant", "link": "/wiki/Apache_Ant"},
{"name": "APL", "link": "/wiki/APL_(programming_language)"},
{"name": "AutoHotkey", "link": "/wiki/AutoHotkey"},
{"name": "AutoIt", "link": "/wiki/AutoIt"},
{"name": "BASIC", "link": "/wiki/BASIC"},
{"name": "Programming Language for Business", "link": "/wiki/Programming_Language_for_Business"},
{"name": "Eiffel", "link": "/wiki/Eiffel_(programming_language)"},
{"name": "EiffelStudio", "link": "/wiki/EiffelStudio"},
{"name": "Emacs Lisp", "link": "/wiki/Emacs_Lisp"},
{"name": "FOCAL", "link": "/wiki/FOCAL_(programming_language)"},
{"name": "GameMaker Language", "link": "/wiki/GameMaker_Studio"},
{"name": "Groovy", "link": "/wiki/Groovy_(programming_language)"},
{"name": "J", "link": "/wiki/J_(programming_language)"},
{"name": "jq", "link": "/wiki/Jq_(programming_language)"},
{"name": "Julia", "link": "/wiki/Julia_(programming_language)"},
{"name": "machine code", "link": "/wiki/Machine_code"},
{"name": "JavaScript", "link": "/wiki/JavaScript"},
{"name": "Lisp", "link": "/wiki/Lisp_(programming_language)"},
{"name": "LPC", "link": "/wiki/LPC_(programming_language)"},
{"name": "Lua", "link": "/wiki/Lua_(programming_language)"},
{"name": "MUMPS", "link": "/wiki/MUMPS"},
{"name": "Maple", "link": "/wiki/Maple_(software)"},
{"name": "Mathematica", "link": "/wiki/Mathematica"},
{"name": "Wolfram language", "link": "/wiki/Wolfram_language"},
{"name": "MATLAB", "link": "/wiki/MATLAB"},
{"name": "OCaml", "link": "/wiki/OCaml"},
{"name": "Pascal", "link": "/wiki/Pascal_(programming_language)"},
{"name": "PCASTL", "link": "/wiki/PCASTL"},
{"name": "Perl", "link": "/wiki/Perl"},
{"name": "PHP", "link": "/wiki/PHP"},
{"name": "PostScript", "link": "/wiki/PostScript"},
{"name": "PowerShell", "link": "/wiki/PowerShell"},
{"name": "PROSE", "link": "/wiki/PROSE_modeling_language"},
{"name": "Python", "link": "/wiki/Python_(programming_language)"},
{"name": "Rexx", "link": "/wiki/Rexx"},
{"name": "R", "link": "/wiki/R_(programming_language)"},
{"name": "REBOL", "link": "/wiki/REBOL"},
{"name": "Ring", "link": "/wiki/Ring_(programming_language)"},
{"name": "Ruby", "link": "/wiki/Ruby_(programming_language)"},
{"name": "S-Lang", "link": "/wiki/S-Lang"},
{"name": "Speakeasy", "link": "/wiki/Speakeasy_(computational_environment)"},
{"name": "Standard ML", "link": "/wiki/Standard_ML"},
{"name": "Spin", "link": "/wiki/Parallax_Propeller"},
{"name": "Tcl", "link": "/wiki/Tcl"},
{"name": "Tea", "link": "/wiki/Tea_(programming_language)"},
{"name": "TorqueScript", "link": "/wiki/TorqueScript"},
{"name": "thinBasic", "link": "/wiki/ThinBasic"},
{"name": "VBScript", "link": "/wiki/VBScript"},
{"name": "Windows PowerShell", "link": "/wiki/Windows_PowerShell"},
{"name": ".NET", "link": "/wiki/.NET"},
{"name": "below", "link": "#Scripting_languages"},
{"name": "Aldor", "link": "/wiki/Aldor"},
{"name": "Alphard", "link": "/wiki/Alphard_(programming_language)"},
{"name": "C++", "link": "/wiki/Generator_(computer_programming)#C++"},
{"name": "C#", "link": "/wiki/Generator_(computer_science)#C#"},
{"name": "CLU", "link": "/wiki/CLU_(programming_language)"},
{"name": "Cobra", "link": "/wiki/Cobra_(programming_language)"},
{"name": "Eiffel", "link": "/wiki/Eiffel_(programming_language)"},
{"name": "Icon", "link": "/wiki/Icon_(programming_language)"},
{"name": "IPL-v", "link": "/wiki/Information_Processing_Language"},
{"name": "jq", "link": "/wiki/Jq_(programming_language)"},
{"name": "Julia", "link": "/wiki/Julia_(programming_language)"},
{"name": "Lua", "link": "/wiki/Lua_(programming_language)"},
{"name": "Nim", "link": "/wiki/Nim_(programming_language)"},
{"name": "PHP", "link": "/wiki/PHP"},
{"name": "Python", "link": "/wiki/Python_(programming_language)"},
{"name": "Sather", "link": "/wiki/Sather"},
{"name": "APL", "link": "/wiki/APL_(programming_language)"},
{"name": "C#", "link": "/wiki/C_Sharp_(programming_language)"},
{"name": "Clean", "link": "/wiki/Clean_(programming_language)"},
{"name": "Crystal", "link": "/wiki/Crystal_(programming_language)"},
{"name": "Dart", "link": "/wiki/Dart_(programming_language)"},
{"name": "ECMAScript", "link": "/wiki/ECMAScript"},
{"name": "Emerald", "link": "/wiki/Emerald_(programming_language)"},
{"name": "Erlang", "link": "/wiki/Erlang_(programming_language)"},
{"name": "Go", "link": "/wiki/Go_(programming_language)"},
{"name": "Groovy", "link": "/wiki/Apache_Groovy"},
{"name": "Haskell", "link": "/wiki/Haskell"},
{"name": "Java", "link": "/wiki/Java_(programming_language)"},
{"name": "Julia", "link": "/wiki/Julia_(programming_language)"},
{"name": "Kotlin", "link": "/wiki/Kotlin_(programming_language)"},
{"name": "LabVIEW", "link": "/wiki/LabVIEW"},
{"name": "Lisp", "link": "/wiki/Lisp_(programming_language)"},
{"name": "Lua", "link": "/wiki/Lua_(programming_language)"},
{"name": "ML", "link": "/wiki/ML_(programming_language)"},
{"name": "Modula-3", "link": "/wiki/Modula-3"},
{"name": "Perl", "link": "/wiki/Perl"},
{"name": "PHP", "link": "/wiki/PHP"},
{"name": "PowerShell", "link": "/wiki/PowerShell"},
{"name": "Python", "link": "/wiki/Python_(programming_language)"},
{"name": "Ring", "link": "/wiki/Ring_(programming_language)"},
{"name": "Ruby", "link": "/wiki/Ruby_(programming_language)"},
{"name": "Smalltalk", "link": "/wiki/Smalltalk"},
{"name": "Speakeasy", "link": "/wiki/Speakeasy"},
{"name": "ARM", "link": "/wiki/ARM_architecture"},
{"name": "DEC", "link": "/wiki/Digital_Equipment_Corporation"},
{"name": "Intel 8008", "link": "/wiki/Intel_8008"},
{"name": "8080", "link": "/wiki/Intel_8080"},
{"name": "8085", "link": "/wiki/Intel_8085"},
{"name": "x86", "link": "/wiki/X86"},
{"name": "IBM", "link": "/wiki/IBM"},
{"name": "MIPS", "link": "/wiki/MIPS_architecture"},
{"name": "Motorola 6800", "link": "/wiki/Motorola_6800"},
{"name": "8-bit", "link": "/wiki/8-bit_computing"},
{"name": "Motorola 68000 family", "link": "/wiki/Motorola_68000_family"},
{"name": "Macintosh", "link": "/wiki/Macintosh"},
{"name": "Sun", "link": "/wiki/Sun_Microsystems"},
{"name": "MOS Technology 65xx", "link": "/wiki/MOS_Technology_65xx"},
{"name": "8-bit", "link": "/wiki/8-bit_computing"},
{"name": "National Semiconductor", "link": "/wiki/National_Semiconductor"},
{"name": "NS320xx", "link": "/wiki/NS320xx"},
{"name": "POWER", "link": "/wiki/IBM_POWER_Instruction_Set_Architecture"},
{"name": "IBM RS/6000", "link": "/wiki/IBM_RS/6000"},
{"name": "Sun Microsystems", "link": "/wiki/Sun_Microsystems"},
{"name": "Oracle", "link": "/wiki/Oracle_Corporation"},
{"name": "SPARC", "link": "/wiki/SPARC"},
{"name": "UNIVAC", "link": "/wiki/UNIVAC"},
{"name": "MCST", "link": "/wiki/Moscow_Center_of_SPARC_Technologies"},
{"name": "Elbrus 2000", "link": "/wiki/Elbrus_2000"},
{"name": "C++", "link": "/wiki/C%2B%2B"},
{"name": "CWIC", "link": "/wiki/Compiler-compiler#CWIC"},
{"name": "Curl", "link": "/wiki/Curl_(programming_language)"},
{"name": "D", "link": "/wiki/D_(programming_language)"},
{"name": "eC", "link": "/wiki/EC_(programming_language)"},
{"name": "Emacs Lisp", "link": "/wiki/Emacs_Lisp"},
{"name": "Elixir", "link": "/wiki/Elixir_(programming_language)"},
{"name": "F#", "link": "/wiki/F_Sharp_(programming_language)"},
{"name": "Groovy", "link": "/wiki/Groovy_(programming_language)"},
{"name": "Haskell", "link": "/wiki/Haskell"},
{"name": "Julia", "link": "/wiki/Julia_(programming_language)"},
{"name": "Lisp", "link": "/wiki/Lisp_(programming_language)"},
{"name": "Lua", "link": "/wiki/Lua_(programming_language)"},
{"name": "Maude system", "link": "/wiki/Maude_system"},
{"name": "Mathematica", "link": "/wiki/Mathematica"},
{"name": "Wolfram language", "link": "/wiki/Wolfram_language"},
{"name": "META II", "link": "/wiki/META_II"},
{"name": "MetaOCaml", "link": "/wiki/MetaOCaml"},
{"name": "Nemerle", "link": "/wiki/Nemerle"},
{"name": "Nim", "link": "/wiki/Nim_(programming_language)"},
{"name": "Perl", "link": "/wiki/Perl"},
{"name": "Python", "link": "/wiki/Python_(programming_language)"},
{"name": "Ring", "link": "/wiki/Ring_(programming_language)"},
{"name": "Ruby", "link": "/wiki/Ruby_(programming_language)"},
{"name": "Rust", "link": "/wiki/Rust_(programming_language)"},
{"name": "Scheme", "link": "/wiki/Scheme_(programming_language)"},
{"name": "SequenceL", "link": "/wiki/SequenceL"},
{"name": "Smalltalk", "link": "/wiki/Smalltalk"},
{"name": "Source", "link": "/wiki/Source_(programming_language)"},
{"name": "TREEMETA", "link": "/wiki/TREE-META"},
{"name": "1C:Enterprise programming language", "link": "/wiki/1C:Enterprise_programming_language"},
{"name": "Ada", "link": "/wiki/Ada_(programming_language)"},
{"name": "concurrent", "link": "/wiki/Concurrent_computing"},
{"name": "distributed", "link": "/wiki/Distributed_computing"},
{"name": "generic", "link": "/wiki/Generic_programming"},
{"name": "template metaprogramming", "link": "/wiki/Template_metaprogramming"},
{"name": "imperative", "link": "/wiki/Imperative_programming"},
{"name": "object-oriented", "link": "/wiki/Object-oriented_programming"},
{"name": "class-based", "link": "/wiki/Class_(computer_science)"},
{"name": "ALF", "link": "/wiki/Algebraic_Logic_Functional_(programming_language)"},
{"name": "functional", "link": "/wiki/Functional_programming"},
{"name": "logic", "link": "/wiki/Logic_programming"},
{"name": "Alma-0", "link": "/wiki/Alma-0"},
{"name": "APL", "link": "/wiki/APL_(programming_language)"},
{"name": "BETA", "link": "/wiki/BETA_(programming_language)"},
{"name": "C++", "link": "/wiki/C%2B%2B"},
{"name": "C#", "link": "/wiki/C_Sharp_(programming_language)"},
{"name": "Ceylon", "link": "/wiki/Ceylon_(programming_language)"},
{"name": "ChucK", "link": "/wiki/ChucK"},
{"name": "Cobra", "link": "/wiki/Cobra_(programming_language)"},
{"name": "Common Lisp", "link": "/wiki/Common_Lisp"},
{"name": "aspect-oriented", "link": "/wiki/Aspect-oriented_programming"},
{"name": "Curl", "link": "/wiki/Curl_(programming_language)"},
{"name": "Curry", "link": "/wiki/Curry_(programming_language)"},
{"name": "D", "link": "/wiki/D_(programming_language)"},
{"name": "Dart", "link": "/wiki/Dart_(programming_language)"},
{"name": "Delphi", "link": "/wiki/Delphi_(programming_language)"},
{"name": "Object Pascal", "link": "/wiki/Object_Pascal"},
{"name": "Dylan", "link": "/wiki/Dylan_(programming_language)"},
{"name": "eC", "link": "/wiki/EC_(programming_language)"},
{"name": "ECMAScript", "link": "/wiki/ECMAScript"},
{"name": "Eiffel", "link": "/wiki/Eiffel_(programming_language)"},
{"name": "F#", "link": "/wiki/F_Sharp_(programming_language)"},
{"name": "Fantom", "link": "/wiki/Fantom_(programming_language)"},
{"name": "Go", "link": "/wiki/Go_(programming_language)"},
{"name": "Groovy", "link": "/wiki/Groovy_(programming_language)"},
{"name": "Harbour", "link": "/wiki/Harbour_(software)"},
{"name": "Hop", "link": "/wiki/Hop_(software)"},
{"name": "J", "link": "/wiki/J_(programming_language)"},
{"name": "Julia", "link": "/wiki/Julia_(programming_language)"},
{"name": "multiple dispatch", "link": "/wiki/Multiple_dispatch"},
{"name": "LabVIEW", "link": "/wiki/LabVIEW"},
{"name": "visual", "link": "/wiki/Visual_programming_language"},
{"name": "dataflow", "link": "/wiki/Dataflow_programming"},
{"name": "Lava", "link": "/wiki/Lava_(programming_language)"},
{"name": "Lua", "link": "/wiki/Lua_(programming_language)"},
{"name": "prototype-based", "link": "/wiki/Prototype-based_programming"},
{"name": "Mathematica", "link": "/wiki/Mathematica"},
{"name": "Wolfram language", "link": "/wiki/Wolfram_language"},
{"name": "Mercury", "link": "/wiki/Mercury_(programming_language)"},
{"name": "Metaobject protocols", "link": "/wiki/Metaobject"},
{"name": "Nemerle", "link": "/wiki/Nemerle"},
{"name": "Objective-C", "link": "/wiki/Objective-C"},
{"name": "OCaml", "link": "/wiki/OCaml"},
{"name": "Oz", "link": "/wiki/Oz_(programming_language)"},
{"name": "eager", "link": "/wiki/Eager_evaluation"},
{"name": "lazy", "link": "/wiki/Lazy_evaluation"},
{"name": "constraint", "link": "/wiki/Constraint_programming"},
{"name": "cross-platform", "link": "/wiki/Cross-platform"},
{"name": "Object Pascal", "link": "/wiki/Object_Pascal"},
{"name": "Perl", "link": "/wiki/Perl"},
{"name": "PHP", "link": "/wiki/PHP"},
{"name": "Pike", "link": "/wiki/Pike_(programming_language)"},
{"name": "Prograph", "link": "/wiki/Prograph"},
{"name": "Python", "link": "/wiki/Python_(programming_language)"},
{"name": "R", "link": "/wiki/R_(programming_language)"},
{"name": "Racket", "link": "/wiki/Racket_(programming_language)"},
{"name": "REBOL", "link": "/wiki/REBOL"},
{"name": "Red", "link": "/wiki/Red_(programming_language)"},
{"name": "ROOP", "link": "/wiki/ROOP_(programming_language)"},
{"name": "Ring", "link": "/wiki/Ring_(programming_language)"},
{"name": "Ruby", "link": "/wiki/Ruby_(programming_language)"},
{"name": "Rust", "link": "/wiki/Rust_(programming_language)"},
{"name": "Scala", "link": "/wiki/Scala_(programming_language)"},
{"name": "Seed7", "link": "/wiki/Seed7"},
{"name": "SISAL", "link": "/wiki/SISAL"},
{"name": "Spreadsheets", "link": "/wiki/Spreadsheet"},
{"name": "Swift", "link": "/wiki/Swift_(programming_language)"},
{"name": "Tcl", "link": "/wiki/Tcl"},
{"name": "Windows PowerShell", "link": "/wiki/Windows_PowerShell"},
{"name": "AIMMS", "link": "/wiki/AIMMS"},
{"name": "AMPL", "link": "/wiki/AMPL_(programming_language)"},
{"name": "Analytica", "link": "/wiki/Analytica_(software)"},
{"name": "Fortran", "link": "/wiki/Fortran"},
{"name": "FreeMat", "link": "/wiki/FreeMat"},
{"name": "GAUSS", "link": "/wiki/GAUSS_(software)"},
{"name": "GAMS", "link": "/wiki/General_Algebraic_Modeling_System"},
{"name": "GNU Octave", "link": "/wiki/GNU_Octave"},
{"name": "Julia", "link": "/wiki/Julia_(programming_language)"},
{"name": "Klerer-May System", "link": "/wiki/Klerer-May_System"},
{"name": "Mathematica", "link": "/wiki/Mathematica"},
{"name": "Wolfram language", "link": "/wiki/Wolfram_language"},
{"name": "MATLAB", "link": "/wiki/MATLAB"},
{"name": "PROSE", "link": "/wiki/PROSE_modeling_language"},
{"name": "R", "link": "/wiki/R_(programming_language)"},
{"name": "Seneca", "link": "/wiki/Oberon_(programming_language)"},
{"name": "Oberon", "link": "/wiki/Oberon_(programming_language)"},
{"name": "Scilab", "link": "/wiki/Scilab"},
{"name": "Speakeasy", "link": "/wiki/Speakeasy"},
{"name": "Common Lisp", "link": "/wiki/Common_Lisp"},
{"name": "Cecil", "link": "/wiki/Cecil_(programming_language)"},
{"name": "Dylan", "link": "/wiki/Dylan_(programming_language)"},
{"name": "Julia", "link": "/wiki/Julia_(programming_language)"},
{"name": "ActionScript 3.0", "link": "/wiki/ActionScript"},
{"name": "Actor", "link": "/wiki/Actor_(programming_language)"},
{"name": "Ada 95", "link": "/wiki/Ada_(programming_language)"},
{"name": "Ada 2005", "link": "/wiki/Ada_(programming_language)"},
{"name": "APL", "link": "/wiki/APL_(programming_language)"},
{"name": "BETA", "link": "/wiki/BETA_(programming_language)"},
{"name": "C++", "link": "/wiki/C%2B%2B"},
{"name": "C#", "link": "/wiki/C_Sharp_(programming_language)"},
{"name": "Ceylon", "link": "/wiki/Ceylon_(programming_language)"},
{"name": "Dart", "link": "/wiki/Dart_(programming_language)"},
{"name": "Oxygene", "link": "/wiki/Oxygene_(programming_language)"},
{"name": "ChucK", "link": "/wiki/ChucK"},
{"name": "Cobra", "link": "/wiki/Cobra_(programming_language)"},
{"name": "ColdFusion", "link": "/wiki/ColdFusion"},
{"name": "Curl", "link": "/wiki/Curl_(programming_language)"},
{"name": "D", "link": "/wiki/D_(programming_language)"},
{"name": "Distributed Application Specification Language", "link": "/wiki/Distributed_Application_Specification_Language"},
{"name": "Delphi", "link": "/wiki/Delphi_(programming_language)"},
{"name": "Object Pascal", "link": "/wiki/Object_Pascal"},
{"name": "E", "link": "/wiki/E_(programming_language)"},
{"name": "GNU E", "link": "/wiki/GNU_E"},
{"name": "eC", "link": "/wiki/EC_(programming_language)"},
{"name": "Eiffel", "link": "/wiki/Eiffel_(programming_language)"},
{"name": "F-Script", "link": "/wiki/F-Script_(programming_language)"},
{"name": "Fortran 2003", "link": "/wiki/Fortran_2003"},
{"name": "Fortress", "link": "/wiki/Fortress_(programming_language)"},
{"name": "Gambas", "link": "/wiki/Gambas"},
{"name": "Game Maker Language", "link": "/wiki/GameMaker:_Studio"},
{"name": "Harbour", "link": "/wiki/Harbour_(software)"},
{"name": "J", "link": "/wiki/J_(programming_language)"},
{"name": "Java", "link": "/wiki/Java_(programming_language)"},
{"name": "LabVIEW", "link": "/wiki/LabVIEW"},
{"name": "Lava", "link": "/wiki/Lava_(programming_language)"},
{"name": "Lua", "link": "/wiki/Lua_(programming_language)"},
{"name": "Modula-2", "link": "/wiki/Modula-2"},
{"name": "Nemerle", "link": "/wiki/Nemerle"},
{"name": "NetRexx", "link": "/wiki/NetRexx"},
{"name": "Oberon-2", "link": "/wiki/Oberon-2_(programming_language)"},
{"name": "Object Pascal", "link": "/wiki/Object_Pascal"},
{"name": "Object REXX", "link": "/wiki/Object_REXX"},
{"name": "Objective-C", "link": "/wiki/Objective-C"},
{"name": "Smalltalk", "link": "/wiki/Smalltalk"},
{"name": "OCaml", "link": "/wiki/OCaml"},
{"name": "OpenEdge Advanced Business Language", "link": "/wiki/OpenEdge_Advanced_Business_Language"},
{"name": "Oz, Mozart Programming System", "link": "/wiki/Oz_(programming_language)"},
{"name": "Perl", "link": "/wiki/Perl"},
{"name": "PHP", "link": "/wiki/PHP"},
{"name": "Pike", "link": "/wiki/Pike_(programming_language)"},
{"name": "Prograph", "link": "/wiki/Prograph"},
{"name": "Python", "link": "/wiki/Python_(programming_language)"},
{"name": "Revolution", "link": "/wiki/Revolution_(programming_language)"},
{"name": "Ring", "link": "/wiki/Ring_(programming_language)"},
{"name": "Ruby", "link": "/wiki/Ruby_(programming_language)"},
{"name": "Scala", "link": "/wiki/Scala_(programming_language)"},
{"name": "Speakeasy", "link": "/wiki/Speakeasy_(computational_environment)"},
{"name": "Simula", "link": "/wiki/Simula"},
{"name": "Ole-Johan Dahl", "link": "/wiki/Ole-Johan_Dahl"},
{"name": "Kristen Nygaard", "link": "/wiki/Kristen_Nygaard"},
{"name": "Smalltalk", "link": "/wiki/Smalltalk"},
{"name": "Xerox PARC", "link": "/wiki/PARC_(company)"},
{"name": "SPIN", "link": "/wiki/Parallax_Propeller"},
{"name": "SuperCollider", "link": "/wiki/SuperCollider"},
{"name": "VBScript", "link": "/wiki/VBScript"},
{"name": "Visual DataFlex", "link": "/wiki/Visual_DataFlex"},
{"name": "Visual FoxPro", "link": "/wiki/Visual_FoxPro"},
{"name": "Visual Prolog", "link": "/wiki/Visual_Prolog"},
{"name": "X++", "link": "/wiki/Microsoft_Dynamics_AX"},
{"name": "Xojo", "link": "/wiki/Xojo"},
{"name": "XOTcl", "link": "/wiki/XOTcl"},
{"name": "1C:Enterprise programming language", "link": "/wiki/1C:Enterprise_programming_language"},
{"name": "Actor-Based Concurrent Language", "link": "/wiki/Actor-Based_Concurrent_Language"},
{"name": "Agora", "link": "/wiki/Agora_(programming_language)"},
{"name": "Cecil", "link": "/wiki/Cecil_(programming_language)"},
{"name": "ECMAScript", "link": "/wiki/ECMAScript"},
{"name": "Etoys", "link": "/wiki/Etoys_(programming_language)"},
{"name": "Squeak", "link": "/wiki/Squeak"},
{"name": "Io", "link": "/wiki/Io_(programming_language)"},
{"name": "Lua", "link": "/wiki/Lua_(programming_language)"},
{"name": "MOO", "link": "/wiki/MOO_(programming_language)"},
{"name": "NewtonScript", "link": "/wiki/NewtonScript"},
{"name": "Obliq", "link": "/wiki/Obliq"},
{"name": "R", "link": "/wiki/R_(programming_language)"},
{"name": "REBOL", "link": "/wiki/REBOL"},
{"name": "Red", "link": "/wiki/Red_(programming_language)"},
{"name": "Self", "link": "/wiki/Self_(programming_language)"},
{"name": "Smalltalk", "link": "/wiki/Smalltalk"},
{"name": "TADS", "link": "/wiki/TADS"},
{"name": "ISWIM", "link": "/wiki/ISWIM"},
{"name": "ABC", "link": "/wiki/ABC_(programming_language)"},
{"name": "Miranda", "link": "/wiki/Miranda_(programming_language)"},
{"name": "Elixir", "link": "/wiki/Elixir_(programming_language)"},
{"name": "F#", "link": "/wiki/F_Sharp_(programming_language)"},
{"name": "Nemerle", "link": "/wiki/Nemerle"},
{"name": "Nim", "link": "/wiki/Nim_(programming_language)"},
{"name": "Occam", "link": "/wiki/Occam_(programming_language)"},
{"name": "SPIN", "link": "/wiki/Parallax_Propeller"},
{"name": "Scala", "link": "/wiki/Scala_(programming_language)"},
{"name": "Ada", "link": "/wiki/Ada_(programming_language)"},
{"name": "ALGOL 58", "link": "/wiki/ALGOL_58"},
{"name": "ALGOL 60", "link": "/wiki/ALGOL_60"},
{"name": "Alma-0", "link": "/wiki/Alma-0"},
{"name": "BASIC", "link": "/wiki/BASIC"},
{"name": "BCPL", "link": "/wiki/BCPL"},
{"name": "BLISS", "link": "/wiki/BLISS"},
{"name": "C", "link": "/wiki/C_(programming_language)"},
{"name": "C++", "link": "/wiki/C%2B%2B"},
{"name": "C#", "link": "/wiki/C_Sharp_(programming_language)"},
{"name": "Ceylon", "link": "/wiki/Ceylon_(programming_language)"},
{"name": "CHILL", "link": "/wiki/CHILL"},
{"name": "ChucK", "link": "/wiki/ChucK"},
{"name": "COBOL", "link": "/wiki/COBOL"},
{"name": "Cobra", "link": "/wiki/Cobra_(programming_language)"},
{"name": "ColdFusion", "link": "/wiki/ColdFusion"},
{"name": "CPL", "link": "/wiki/CPL_(programming_language)"},
{"name": "Curl", "link": "/wiki/Curl_(programming_language)"},
{"name": "D", "link": "/wiki/D_(programming_language)"},
{"name": "Distributed Application Specification Language", "link": "/wiki/Distributed_Application_Specification_Language"},
{"name": "declarative programming", "link": "/wiki/Declarative_programming"},
{"name": "imperative programming", "link": "/wiki/Imperative_programming"},
{"name": "eC", "link": "/wiki/EC_(programming_language)"},
{"name": "ECMAScript", "link": "/wiki/ECMAScript"},
{"name": "Eiffel", "link": "/wiki/Eiffel_(programming_language)"},
{"name": "Forth", "link": "/wiki/Forth_(programming_language)"},
{"name": "Fortran", "link": "/wiki/Fortran"},
{"name": "GAUSS", "link": "/wiki/GAUSS_(software)"},
{"name": "Go", "link": "/wiki/Go_(programming_language)"},
{"name": "Harbour", "link": "/wiki/Harbour_(software)"},
{"name": "HyperTalk", "link": "/wiki/HyperTalk"},
{"name": "Java", "link": "/wiki/Java_(programming_language)"},
{"name": "JOVIAL", "link": "/wiki/JOVIAL"},
{"name": "Julia", "link": "/wiki/Julia_(programming_language)"},
{"name": "Language H", "link": "/wiki/Language_H"},
{"name": "Lasso", "link": "/wiki/Lasso_(programming_language)"},
{"name": "Modula-2", "link": "/wiki/Modula-2"},
{"name": "Mathematica", "link": "/wiki/Mathematica"},
{"name": "Wolfram language", "link": "/wiki/Wolfram_language"},
{"name": "MATLAB", "link": "/wiki/MATLAB"},
{"name": "Mesa", "link": "/wiki/Mesa"},
{"name": "MUMPS", "link": "/wiki/MUMPS"},
{"name": "Nemerle", "link": "/wiki/Nemerle"},
{"name": "Nim", "link": "/wiki/Nim_(programming_language)"},
{"name": "Oberon", "link": "/wiki/Oberon_(programming_language)"},
{"name": "Oberon-2", "link": "/wiki/Oberon-2"},
{"name": "OCaml", "link": "/wiki/OCaml"},
{"name": "Occam", "link": "/wiki/Occam_(programming_language)"},
{"name": "Oriel", "link": "/wiki/Oriel_(scripting_language)"},
{"name": "Pascal", "link": "/wiki/Pascal_(programming_language)"},
{"name": "PCASTL", "link": "/wiki/PCASTL"},
{"name": "Perl", "link": "/wiki/Perl"},
{"name": "Pike", "link": "/wiki/Pike_(programming_language)"},
{"name": "PL/C", "link": "/wiki/PL/C"},
{"name": "PL/I", "link": "/wiki/PL/I"},
{"name": "Plus", "link": "/wiki/Plus_(programming_language)"},
{"name": "PowerShell", "link": "/wiki/PowerShell"},
{"name": "PROSE", "link": "/wiki/PROSE_modeling_language"},
{"name": "Python", "link": "/wiki/Python_(programming_language)"},
{"name": "R", "link": "/wiki/R_(programming_language)"},
{"name": "Rapira", "link": "/wiki/Rapira"},
{"name": "RPG", "link": "/wiki/IBM_RPG"},
{"name": "Rust", "link": "/wiki/Rust_(programming_language)"},
{"name": "S-Lang", "link": "/wiki/S-Lang"},
{"name": "VBScript", "link": "/wiki/VBScript"},
{"name": "Visual Basic", "link": "/wiki/Visual_Basic"},
{"name": "Visual FoxPro", "link": "/wiki/Visual_FoxPro"},
{"name": "Microsoft Dynamics AX", "link": "/wiki/Microsoft_Dynamics_AX"},
{"name": "Befunge", "link": "/wiki/Befunge"},
{"name": "Ceylon", "link": "/wiki/Ceylon_(programming_language)"},
{"name": "Charm", "link": "/wiki/Charm_(language)"},
{"name": "ChucK", "link": "/wiki/ChucK"},
{"name": "CLI", "link": "/wiki/List_of_CLI_languages"},
{"name": "Cobra", "link": "/wiki/Cobra_(programming_language)"},
{"name": "Component Pascal", "link": "/wiki/Component_Pascal"},
{"name": "BlackBox Component Builder", "link": "/wiki/BlackBox_Component_Builder"},
{"name": "Curl", "link": "/wiki/Curl_(programming_language)"},
{"name": "Cypher", "link": "/wiki/Cypher_(query_language)"},
{"name": "Delphi", "link": "/wiki/Delphi_(programming_language)"},
{"name": "Object Pascal", "link": "/wiki/Object_Pascal"},
{"name": "eC", "link": "/wiki/EC_(programming_language)"},
{"name": "ECMAScript", "link": "/wiki/ECMAScript"},
{"name": "Emacs Lisp", "link": "/wiki/Emacs_Lisp"},
{"name": "Eiffel", "link": "/wiki/Eiffel_(programming_language)"},
{"name": "Harbour", "link": "/wiki/Harbour_(software)"},
{"name": "Julia", "link": "/wiki/Julia_(programming_language)"},
{"name": "JVM", "link": "/wiki/List_of_JVM_languages"},
{"name": "Lisp", "link": "/wiki/Lisp_(programming_language)"},
{"name": "Lua", "link": "/wiki/Lua_(programming_language)"},
{"name": "Mathematica", "link": "/wiki/Mathematica"},
{"name": "Wolfram language", "link": "/wiki/Wolfram_language"},
{"name": "Maude system", "link": "/wiki/Maude_system"},
{"name": "Oberon-2", "link": "/wiki/Oberon-2_(programming_language)"},
{"name": "Objective-C", "link": "/wiki/Objective-C"},
{"name": "PCASTL", "link": "/wiki/PCASTL"},
{"name": "Perl", "link": "/wiki/Perl"},
{"name": "PHP", "link": "/wiki/PHP"},
{"name": "Pico", "link": "/wiki/Pico_(programming_language)"},
{"name": "Poplog", "link": "/wiki/Poplog"},
{"name": "PowerShell", "link": "/wiki/PowerShell"},
{"name": "Prolog", "link": "/wiki/Prolog"},
{"name": "Python", "link": "/wiki/Python_(programming_language)"},
{"name": "REBOL", "link": "/wiki/REBOL"},
{"name": "Red", "link": "/wiki/Red_(programming_language)"},
{"name": "Ring", "link": "/wiki/Ring_(programming_language)"},
{"name": "Ruby", "link": "/wiki/Ruby_(programming_language)"},
{"name": "Smalltalk", "link": "/wiki/Smalltalk"},
{"name": "Xerox PARC", "link": "/wiki/PARC_(company)"},
{"name": "Snobol", "link": "/wiki/SNOBOL"},
{"name": "Tcl", "link": "/wiki/Tcl"},
{"name": "XOTcl", "link": "/wiki/XOTcl"},
{"name": "X++", "link": "/wiki/Microsoft_Dynamics_AX"},
{"name": "Xojo", "link": "/wiki/Xojo"},
{"name": "awk", "link": "/wiki/Awk"},
{"name": "CLIPS", "link": "/wiki/CLIPS"},
{"name": "Claire", "link": "/wiki/Claire_(programming_language)"},
{"name": "Constraint Handling Rules", "link": "/wiki/Constraint_Handling_Rules"},
{"name": "Drools", "link": "/wiki/Drools"},
{"name": "GOAL agent programming language", "link": "/wiki/GOAL_agent_programming_language"},
{"name": "Jess", "link": "/wiki/Jess_(programming_language)"},
{"name": "Mathematica", "link": "/wiki/Mathematica"},
{"name": "Wolfram language", "link": "/wiki/Wolfram_language"},
{"name": "OPS5", "link": "/wiki/OPS5"},
{"name": "Prolog", "link": "/wiki/Prolog"},
{"name": "ToonTalk", "link": "/wiki/ToonTalk"},
{"name": "AngelScript", "link": "/wiki/AngelScript"},
{"name": "AppleScript", "link": "/wiki/AppleScript"},
{"name": "AutoHotKey", "link": "/wiki/AutoHotKey"},
{"name": "AutoIt", "link": "/wiki/AutoIt"},
{"name": "AWK", "link": "/wiki/AWK"},
{"name": "bc", "link": "/wiki/Bc_(programming_language)"},
{"name": "BeanShell", "link": "/wiki/BeanShell"},
{"name": "Bash", "link": "/wiki/Bash_(Unix_shell)"},
{"name": "Ch", "link": "/wiki/Ch_(computer_programming)"},
{"name": "CLI", "link": "/wiki/List_of_CLI_languages"},
{"name": "CLIST", "link": "/wiki/CLIST"},
{"name": "ColdFusion", "link": "/wiki/ColdFusion"},
{"name": "ECMAScript", "link": "/wiki/ECMAScript"},
{"name": "Emacs Lisp", "link": "/wiki/Emacs_Lisp"},
{"name": "CMS EXEC", "link": "/wiki/CMS_EXEC"},
{"name": "EXEC 2", "link": "/wiki/EXEC_2"},
{"name": "F-Script", "link": "/wiki/F-Script_(programming_language)"},
{"name": "Game Maker Language", "link": "/wiki/GameMaker:_Studio"},
{"name": "GDScript", "link": "/wiki/Godot_(game_engine)#GDScript"},
{"name": "Io", "link": "/wiki/Io_(programming_language)"},
{"name": "JASS", "link": "/wiki/JASS_(scripting_language)"},
{"name": "Julia", "link": "/wiki/Julia_(programming_language)"},
{"name": "machine code", "link": "/wiki/Machine_code"},
{"name": "JVM", "link": "/wiki/List_of_JVM_languages"},
{"name": "Ksh", "link": "/wiki/KornShell"},
{"name": "Lasso", "link": "/wiki/Lasso_(programming_language)"},
{"name": "Lua", "link": "/wiki/Lua_(programming_language)"},
{"name": "MAXScript", "link": "/wiki/MAXScript"},
{"name": "MEL", "link": "/wiki/Maya_Embedded_Language"},
{"name": "Object REXX", "link": "/wiki/Object_REXX"},
{"name": "Oriel", "link": "/wiki/Oriel_(scripting_language)"},
{"name": "Pascal Script", "link": "/wiki/Pascal_Script"},
{"name": "Perl", "link": "/wiki/Perl"},
{"name": "PHP", "link": "/wiki/PHP"},
{"name": "PowerShell", "link": "/wiki/PowerShell"},
{"name": "Python", "link": "/wiki/Python_(programming_language)"},
{"name": "R", "link": "/wiki/R_(programming_language)"},
{"name": "REBOL", "link": "/wiki/REBOL"},
{"name": "Red", "link": "/wiki/Red_(programming_language)"},
{"name": "Rexx", "link": "/wiki/Rexx"},
{"name": "Revolution", "link": "/wiki/Revolution_(programming_language)"},
{"name": "Ring", "link": "/wiki/Ring_(programming_language)"},
{"name": "Ruby", "link": "/wiki/Ruby_(programming_language)"},
{"name": "S-Lang", "link": "/wiki/S-Lang"},
{"name": "sed", "link": "/wiki/Sed"},
{"name": "Sh", "link": "/wiki/Bourne_shell"},
{"name": "Smalltalk", "link": "/wiki/Smalltalk"},
{"name": "Squirrel", "link": "/wiki/Squirrel_(programming_language)"},
{"name": "Tea", "link": "/wiki/Tea_(programming_language)"},
{"name": "Tcl", "link": "/wiki/Tcl"},
{"name": "TorqueScript", "link": "/wiki/TorqueScript_(programming_language)"},
{"name": "VBScript", "link": "/wiki/VBScript"},
{"name": "WebDNA", "link": "/wiki/WebDNA"},
{"name": "Windows PowerShell", "link": "/wiki/Windows_PowerShell"},
{"name": ".NET", "link": "/wiki/.NET_Framework"},
{"name": "Unix shell", "link": "/wiki/Unix_shell"},
{"name": "DIGITAL Command Language", "link": "/wiki/DIGITAL_Command_Language"},
{"name": "Beatnik", "link": "/wiki/Beatnik_(programming_language)"},
{"name": "Befunge", "link": "/wiki/Befunge"},
{"name": "Factor", "link": "/wiki/Factor_(programming_language)"},
{"name": "Forth", "link": "/wiki/Forth_(programming_language)"},
{"name": "Joy", "link": "/wiki/Joy_(programming_language)"},
{"name": "Piet", "link": "/wiki/Piet_(programming_language)"},
{"name": "Poplog", "link": "/wiki/Poplog"},
{"name": "POP-11", "link": "/wiki/POP-11"},
{"name": "PostScript", "link": "/wiki/PostScript"},
{"name": "RPL", "link": "/wiki/RPL_(programming_language)"},
{"name": "S-Lang", "link": "/wiki/S-Lang"},
{"name": "Adobe Graphics Assembly Language", "link": "/wiki/Adobe_Graphics_Assembly_Language"},
{"name": "ARB assembly language", "link": "/wiki/ARB_assembly_language"},
{"name": "OpenGL Shading Language", "link": "/wiki/OpenGL_Shading_Language"},
{"name": "High-Level Shading Language", "link": "/wiki/High-Level_Shading_Language"},
{"name": "PlayStation Shader Language", "link": "/wiki/PlayStation_Shader_Language"},
{"name": "Metal Shading Language", "link": "/wiki/Metal_(API)"},
{"name": "Cg", "link": "/wiki/Cg_(programming_language)"},
{"name": "RenderMan Shading Language", "link": "/wiki/RenderMan_Shading_Language"},
{"name": "Gelato Shading Language", "link": "/wiki/Gelato_(software)"},
{"name": "Open Shading Language", "link": "/wiki/Open_Shading_Language"},
{"name": "ATL", "link": "/wiki/ATLAS_Transformation_Language"},
{"name": "AWK", "link": "/wiki/AWK"},
{"name": "MOFM2T", "link": "/wiki/MOFM2T"},
{"name": "QVT", "link": "/wiki/QVT"},
{"name": "Analytica", "link": "/wiki/Analytica_(software)"},
{"name": "Blockly", "link": "/wiki/Blockly"},
{"name": "Clickteam Fusion", "link": "/wiki/Clickteam"},
{"name": "DRAKON", "link": "/wiki/DRAKON"},
{"name": "Fabrik", "link": "/wiki/Fabrik_(software)"},
{"name": "LabVIEW", "link": "/wiki/LabVIEW"},
{"name": "Grasshopper", "link": "/wiki/Grasshopper_3D"},
{"name": "Lava", "link": "/wiki/Lava_(programming_language)"},
{"name": "Max", "link": "/wiki/Max_(software)"},
{"name": "NXT-G", "link": "/wiki/NXT-G"},
{"name": "Pict", "link": "/wiki/Pict_(programming_language)"},
{"name": "Prograph", "link": "/wiki/Prograph"},
{"name": "Pure Data", "link": "/wiki/Pure_Data"},
{"name": "Quartz Composer", "link": "/wiki/Quartz_Composer"},
{"name": "Scratch", "link": "/wiki/Scratch_(programming_language)"},
{"name": "Squeak", "link": "/wiki/Squeak"},
{"name": "Smalltalk", "link": "/wiki/Smalltalk"},
{"name": "Snap!", "link": "/wiki/Snap!_(programming_language)"},
{"name": "Simulink", "link": "/wiki/Simulink"},
{"name": "Spreadsheets", "link": "/wiki/Spreadsheet"},
{"name": "Stateflow", "link": "/wiki/Stateflow"},
{"name": "Subtext", "link": "/wiki/Subtext_(programming_language)"},
{"name": "ToonTalk", "link": "/wiki/ToonTalk"},
{"name": "VEE", "link": "/wiki/Agilent_VEE"},
{"name": "VisSim", "link": "/wiki/VisSim"},
{"name": "Vvvv", "link": "/wiki/Vvvv"},
{"name": "XOD", "link": "/wiki/XOD_(programming_language)"},
{"name": "EICASLAB", "link": "/wiki/EICASLAB"},
{"name": "ALGOL W", "link": "/wiki/ALGOL_W"},
{"name": "Euler", "link": "/wiki/Euler_(programming_language)"},
{"name": "Modula", "link": "/wiki/Modula"},
{"name": "Oberon", "link": "/wiki/Oberon_(programming_language)"},
{"name": "Pascal", "link": "/wiki/Pascal_(programming_language)"},
{"name": "Ant", "link": "/wiki/Apache_Ant"},
{"name": "Cω", "link": "/wiki/C%CF%89"},
{"name": "ECMAScript for XML", "link": "/wiki/ECMAScript_for_XML"},
{"name": "MXML", "link": "/wiki/MXML"},
{"name": "LZX", "link": "/wiki/OpenLaszlo"},
{"name": "XAML", "link": "/wiki/XAML"},
{"name": "XPath", "link": "/wiki/XPath"},
{"name": "XQuery", "link": "/wiki/XQuery"},
{"name": "XProc", "link": "/wiki/XProc"},
{"name": "XSLT", "link": "/wiki/XSLT"}
]